docs_extractor/__init__.py
docs_extractor/cli.py
docs_extractor/core.py
docs_extractor/utils.py
docs_extractor-0.1.1.dist-info/METADATA
docs_extractor-0.1.1.dist-info/WHEEL
docs_extractor-0.1.1.dist-info/entry_points.txt
docs_extractor-0.1.1.dist-info/top_level.txt
docs_extractor-0.1.1.dist-info/RECORD
